pixelyai_serve/__init__.py
pixelyai_serve/serving/__init__.py
pixelyai_serve/serving/jax_module.py
pixelyai_serve/serving/torch_module.py
pixelyai_serve/serving/utils.py
pixelyai_serve-0.0.8.dist-info/LICENSE
pixelyai_serve-0.0.8.dist-info/METADATA
pixelyai_serve-0.0.8.dist-info/WHEEL
pixelyai_serve-0.0.8.dist-info/top_level.txt
pixelyai_serve-0.0.8.dist-info/RECORD
